alu.v

`define NOT not #10 //fundamental, one input
`define NAND nand #20 //fundamental, 2 input
`define NOR nor #20 //fundamental, 2 input
`define AND and #30 //made from inverter and NAND
`define OR or #30 // made from inverter and OR
`define XOR xor #60 //worst case three and gates



/*behavioral verilog done for test bench crafting/checking*/
module behavioraladder32(
   // Outputs
   result,
   // Inputs
   a, b
   );
   input[31:0] a;
   input[31:0] b;
   output [31:0] result;
   wire [32:0] sum = {1'b0,a} + {1'b0,b};
   assign      result = sum[32] ? sum[32:1]: sum[31:0];
endmodule // adder32

module behavioralsubtract32(
   // Outputs
   result,
   // Inputs
   a, b
   );
   input[31:0] a;
   input[31:0] b;
   output [31:0] result;
   wire [32:0] sum = {1'b0,a} - {1'b0,b};
   assign      result = sum[32] ? sum[32:1]: sum[31:0];
endmodule // adder32

module nand32
(
output reg carryout=0,
output reg overflow=0,
output[31:0] andResult,
input [31:0] operandA,
input [31:0] operandB
);
genvar i;
  generate
  //ands all 32 bits
    for (i = 0; i < 32; i = i+1)
    begin : gen1
      `NAND(andResult[i],operandA[i],operandB[i]);
    end
  endgenerate
endmodule

module nor32
(
output reg carryout=0,
output reg overflow=0,
output[31:0] andResult,
input [31:0] operandA,
input [31:0] operandB
);
genvar i;
  generate
  //ands all 32 bits
    for (i = 0; i < 32; i = i+1)
    begin : gen1
      `NOR(andResult[i],operandA[i],operandB[i]);
    end
  endgenerate
endmodule


/*'''Our real code starts here'''*/

module ALU
(
output[31:0]    result,
output          carryout,
output          zero,
output          overflow,
input[31:0]     operandA,
input[31:0]     operandB,
input[2:0]      command

);

endmodule


module and32 //Works for AND, NAND : For AND, M = 0. For NAND, M = 1.
(
output reg carryout=0,
output reg overflow=0,
output[31:0] andResult,
input [31:0] operandA,
input [31:0] operandB,
input M
);
wire [31:0] midResult;
genvar i;
  generate
  //ands all 32 bits
    for (i = 0; i < 32; i = i+1)
    begin : gen1
      `AND(midResult[i],operandA[i],operandB[i]);
      `XOR(andResult[i],midResult[i],M);
    end
  endgenerate
endmodule

module or32 //Works for OR, NOR : For OR, M = 0. For NOR, M = 1.
(
output reg carryout=0,
output reg overflow=0,
output[31:0] andResult,
input [31:0] operandA,
input [31:0] operandB,
input M
);
wire [31:0] midResult;
genvar i;
  generate
  //ands all 32 bits
    for (i = 0; i < 32; i = i+1)
    begin : gen1
      `OR(midResult[i],operandA[i],operandB[i]);
      `XOR(andResult[i],midResult[i],M);
    end
  endgenerate
endmodule





module xor32
(
output[31:0] andResult,
input [31:0] operandA,
input [31:0] operandB
);
genvar i;
  generate
  //ands all 32 bits
    for (i = 0; i < 32; i = i+1)
    begin : gen1
      `XOR(andResult[i],operandA[i],operandB[i]);
    end
  endgenerate
endmodule

module xor1a32
(
output[31:0] andResult,
input [31:0] operandA,
input operandB
);
genvar i;
  generate
  //ands all 32 bits
    for (i = 0; i < 32; i = i+1)
    begin : gen1
      `XOR(andResult[i],operandA[i],operandB);
    end
  endgenerate
endmodule

module structuralFullAdder
(
  // This is the unit module which the FullAdder4bit runs 4 times
    output sum,
    output carryout,
    input a,
    input b,
    input carryin
);
wire AxorB, AxorBandcarryin, AandB;
// XOR gate is true only if one of the two inputs is true, not both
`XOR xorgate1(AxorB, a, b);
`XOR xorgate2(sum, AxorB, carryin);
// AND gate is true only if both inputs are true
`AND andgate1(AxorBandcarryin, AxorB, carryin);
`AND andgate2(AandB, a, b);
/// OR gate is true if either or both of the inputs are true
`OR orgate(carryout, AxorBandcarryin, AandB);
endmodule

module add32
(
output carryout,
output overflow,
output[30:0] carryoutin,
output[31:0] andResult,
output[31:0] MxorB,
input [31:0] operandA,
input [31:0] operandB,
input M

);
wire[30:0] carryoutin;
wire carryout;
wire overflow;
/*wire[31:0] carryoutin;*/
wire[31:0] MxorB;
xor1a32 myxor(MxorB,operandB, M);
structuralFullAdder add0(andResult[0], carryoutin[0], operandA[0],MxorB[0], M);
genvar i;
  generate
  //ands all 32 bits
    for (i = 1; i < 31; i = i+1)
    begin : gen1
      structuralFullAdder addgates(andResult[i], carryoutin[i], operandA[i],MxorB[i], carryoutin[i-1]);
    end
  endgenerate
structuralFullAdder add31(andResult[31], carryout, operandA[31],MxorB[31], carryoutin[30]);

  `XOR overflowgate(overflow,carryoutin[30],carryout);
endmodule


module xort
(
output result,
input a,
input b

);
`XOR xorgate(result,a,b);
endmodule

alu.t.v
`timescale 1 ns / 1 ps
`include "alu.v"
/*include "genvartest.v"*/

/*module testALU();
    reg[31:0] operandA, operandB;
    reg[2:0] command;
    wire[31:0] result;
    wire carryout, zero, overflow;

    ALU myALU (result, carryout, zero, overflow, operandA, operandB, command);

    initial begin
    //dump to vcd file so we can look at waveform
    $dumpfile("alu.vcd");
    $dumpvars(0, testALU);

    $display("   operandA   operandB   |  command   ||  zero   carryout   overflow  | result ||   Exp zero   Exp carryout   Exp overflow   |   Exp result");

    $display("Adder Test:");

    // this is our test bench
    operandA=32'b11;operandB=32'b101; #1000
    $display(" %b %b |  %b      ||      %b    %b    %b    %b   |     %b     ||     0     0     0     |   0 ", operandA, operandB, command, zero, carryout, overflow, result);

    $display("Control Test:");
    operandA=32'b11;operandB=32'b101; #1000
    $display(" %b %b |  %b      ||      %b    %b    %b    %b   |     %b     ||     0     0     0     |   0 ", operandA, operandB, command, zero, carryout, overflow, result);
    end
endmodule*/


/*module testadd();
    reg[31:0] a, b;
    wire[31:0] result;


    adder32 myALU (result, a, b);

    initial begin
    //dump to vcd file so we can look at waveform
    $dumpfile("alu.vcd");
    $dumpvars(0, testadd);



    $display("Adder Test:");
    $display("     a          b     |   result   ||   Exp result");

    a='h0;b='h0; #1000
    $display(" %h   %h  |  %h  ||    00000000", a, b, result);
    a='h0;b='h1; #1000
    $display(" %h   %h  |  %h  ||    00000001", a, b, result);
    a='h1;b='h1; #1000
    $display(" %h   %h  |  %h  ||    00000002", a, b, result);
    a='h1100010;b='h0101010; #1000
    $display(" %h   %h  |  %h  ||    01201020", a, b, result);
    a='h11111111;b='h1; #1000
    $display(" %h   %h  |  %h  ||    11111112", a, b, result);
    a='h92946327;b='h90997372; #1000
    $display(" %h   %h  |  %h  ||    9196eb4c", a, b, result);


    end
endmodule*/

/*'''Completed, working'''*/
/*module testand();
    wire carryout;
    wire overflow;
    wire[31:0] andResult;
    reg [31:0] operandA;
    reg [31:0] operandB;


    and32 myALU (carryout, overflow, andResult, operandA, operandB);

    initial begin
    //dump to vcd file so we can look at waveform
    $dumpfile("alu.vcd");
    $dumpvars(0, testand);
    $display(" operandA   operandB  |  result  ||   Exp result");

    operandA='h0;operandB='h0; #1000
    $display(" %h   %h  | %h ||    00000000", operandA,operandB,  andResult);
    operandA='h181;operandB='h263; #1000
    $display(" %h   %h  | %h ||    00000001", operandA,operandB,  andResult);
    operandA='h161;operandB='h161; #1000
    $display(" %h   %h  | %h ||    00000161", operandA,operandB,  andResult);
    operandA='hffffffff;operandB='hf00f001; #1000
    $display(" %h   %h  | %h ||    0f00f001", operandA,operandB,  andResult);
    operandA='hffffffff;operandB='hcccccccc; #1000
    $display(" %h   %h  | %h ||    cccccccc", operandA,operandB,  andResult);
    end
endmodule*/
/*
module testor();
    wire carryout;
    wire overflow;
    wire[31:0] andResult;
    reg [31:0] operandA;
    reg [31:0] operandB;


    or32 myALU (carryout, overflow, andResult, operandA, operandB);

    initial begin
    //dump to vcd file so we can look at waveform
    $dumpfile("alu.vcd");
    $dumpvars(0, testor);
    $display(" operandA   operandB  |  result  ||   Exp result");

    operandA='h0;operandB='h0; #1000
    $display(" %h   %h  | %h ||    00000000", operandA,operandB,  andResult);
    operandA='h181;operandB='h263; #1000
    $display(" %h   %h  | %h ||    000003e3", operandA,operandB,  andResult);
    operandA='h161;operandB='h161; #1000
    $display(" %h   %h  | %h ||    00000161", operandA,operandB,  andResult);
    operandA='hffffffff;operandB='hf00f001; #1000
    $display(" %h   %h  | %h ||    ffffffff", operandA,operandB,  andResult);
    operandA='hffffffff;operandB='hcccccccc; #1000
    $display(" %h   %h  | %h ||    ffffffff", operandA,operandB,  andResult);
    end
endmodule*/


module testor();
    wire carryout;
    wire overflow;
    wire[31:0] andResult;
    reg [31:0] operandA;
    reg [31:0] operandB;
    reg M;


    or32 myALU (carryout, overflow, andResult, operandA, operandB, M);

    initial begin
    //dump to vcd file so we can look at waveform
    $dumpfile("alu.vcd");
    $dumpvars(0, testor);
    $display(" operandA   operandB  |  result  ||   Exp result");

    operandA='h0;operandB='h0;M=1; #1000
    $display(" %h   %h  | %h ||    ffffffff", operandA,operandB,  andResult);
    operandA='h181;operandB='h263;M=1; #1000
    $display(" %h   %h  | %h ||    fffffc1c", operandA,operandB,  andResult);
    operandA='h161;operandB='h161;M=1; #1000
    $display(" %h   %h  | %h ||    fffffe9e", operandA,operandB,  andResult);
    operandA='hffffffff;operandB='hf00f001;M=1; #1000
    $display(" %h   %h  | %h ||    00000000", operandA,operandB,  andResult);
    operandA='hffffffff;operandB='hcccccccc;M=1; #1000
    $display(" %h   %h  | %h ||    00000000", operandA,operandB,  andResult);
    end
endmodule


/*
module testxor();
    wire carryout;
    wire overflow;
    wire[31:0] andResult;
    reg [31:0] operandA;
    reg [31:0] operandB;


    xor32 myALU (carryout, overflow, andResult, operandA, operandB);

    initial begin
    //dump to vcd file so we can look at waveform
    $dumpfile("alu.vcd");
    $dumpvars(0, testxor);
    $display(" operandA   operandB  |  result  ||   Exp result");

    operandA='h0;operandB='h0; #1000
    $display(" %h   %h  | %h ||    ffffffff", operandA,operandB,  andResult);
    operandA='h181;operandB='h263; #1000
    $display(" %h   %h  | %h ||    fffffffe", operandA,operandB,  andResult);
    operandA='h161;operandB='h161; #1000
    $display(" %h   %h  | %h ||    fffffe9e", operandA,operandB,  andResult);
    operandA='hffffffff;operandB='hf00f001; #1000
    $display(" %h   %h  | %h ||    f0ff0ffe", operandA,operandB,  andResult);
    operandA='hffffffff;operandB='hcccccccc; #1000
    $display(" %h   %h  | %h ||    33333333", operandA,operandB,  andResult);
    end
endmodule*/


/*module testand();
    wire carryout;
    wire overflow;
    wire[31:0] andResult;
    reg [31:0] operandA;
    reg [31:0] operandB;
    reg M;


    and32 myALU (carryout, overflow, andResult, operandA, operandB, M);

    initial begin
    //dump to vcd file so we can look at waveform
    $dumpfile("alu.vcd");
    $dumpvars(0, testand);
    $display(" operandA   operandB  |  result  ||   Exp result");

    operandA='h0;operandB='h0;M=1; #1000
    $display(" %h   %h  | %h ||    ffffffff", operandA,operandB,  andResult);
    operandA='h181;operandB='h263;M=1; #1000
    $display(" %h   %h  | %h ||    fffffffe", operandA,operandB,  andResult);
    operandA='h161;operandB='h161;M=1; #1000
    $display(" %h   %h  | %h ||    fffffe9e", operandA,operandB,  andResult);
    operandA='hffffffff;operandB='hf00f001;M=1; #1000
    $display(" %h   %h  | %h ||    f0ff0ffe", operandA,operandB,  andResult);
    operandA='hffffffff;operandB='hcccccccc;M=1; #1000
    $display(" %h   %h  | %h ||    33333333", operandA,operandB,  andResult);
    end
endmodule*/
/*
module testadd();
    wire carryout;
    wire overflow;
    wire[31:0] andResult;
    reg [31:0] operandA;
    reg [31:0] operandB;

    add32 myALU (carryout, overflow, andResult, operandA, operandB);

    initial begin
    //dump to vcd file so we can look at waveform
    $dumpfile("alu.vcd");
    $dumpvars(0, testadd);
    $display("     a          b     | overflow   carryout |  result  ||   Exp result");

    operandA='h0;operandB='h0; #1000
    $display(" %h   %h  |     %h         %h     | %h ||    00000000", operandA,operandB,  overflow, carryout, andResult);
    operandA='h181;operandB='h263; #1000
    $display(" %h   %h  |     %h         %h     | %h ||    000003e4", operandA,operandB,  overflow, carryout, andResult);
    operandA='h161;operandB='h161; #1000
    $display(" %h   %h  |     %h         %h     | %h ||    000002c2", operandA,operandB,  overflow, carryout, andResult);
    operandA='hffffffff;operandB='hf00f001; #1000
    $display(" %h   %h  |     %h         %h     | %h ||    0f00f000", operandA,operandB,  overflow, carryout, andResult);
    operandA='hffffffff;operandB='hcccccccc; #1000
    $display(" %h   %h  |     %h         %h     | %h ||    cccccccb", operandA,operandB,  overflow, carryout, andResult);
    operandA='hffffffff;operandB='hffffffff; #1000
    $display(" %h   %h  |     %h         %h     | %h ||    fffffffe", operandA,operandB,  overflow, carryout, andResult);
    operandA='hc0000000;operandB='h80000000; #1000
    $display(" %h   %h  |     %h         %h     | %h ||    40000000", operandA,operandB,  overflow, carryout, andResult);
    end
endmodule

/**/
/*module testsubtract();
    wire carryout;
    wire overflow;
    wire[31:0] andResult;
    reg [31:0] operandA;
    reg [31:0] operandB;
    reg M;

    add32 myALU (carryout, overflow, andResult, operandA, operandB, M);

    initial begin
    //dump to vcd file so we can look at waveform
    $dumpfile("alu.vcd");
    $dumpvars(0, testsubtract);
    $display("     a          b      M  | overflow   carryout |  result  ||   Exp result");

    operandA='h01;operandB='h0;M=1; #1000
    $display(" %h   %h   %h  |     %h         %h     | %h ||    00000000", operandA,operandB, M, overflow, carryout, andResult);

    end
endmodule
*/


/*module testxor();
    reg a;
    reg b;
    wire result;

    xort myxor (result, a, b);
    initial begin
    $display("     a    b   |  result  ");

    a = 0;b= 0; #1000
    $display(" %h   %h     %h       ", a, b, result);
    end
endmodule*/

/*'''test skeleton'''*/
/*module testadd();
    wire carryout;
    wire overflow;
    wire[30:0] carryoutin;
    wire[31:0] andResult;
    wire[31:0] MxorB;
    reg [31:0] operandA;
    reg [31:0] operandB;
    reg M;



    add32 myALU (carryout, overflow, carryoutin, andResult, MxorB, operandA, operandB, M);

    initial begin
    //dump to vcd file so we can look at waveform
    $dumpfile("alu.vcd");
    $dumpvars(0, testadd);
    $display("     a          b        M      MxorB   carryoutin | overflow   carryout |  result  ||   Exp result");

    operandA='h00000011;operandB='h001;M=1; #100000
    $display(" %h   %h     %h    %h   | %h    %h         %h     | %h ||    00000000", operandA,operandB, M, MxorB,carryoutin, overflow, carryout, andResult);
    operandA='h181;operandB='h263;M=1; #1000
    $display(" %b   %b     %h    %h   | %b    %h         %h     | %b ||    00000000", operandA,operandB, M, MxorB,carryoutin, overflow, carryout, andResult);
    operandA='h161;operandB='h161;M=1; #1000
    $display(" %b   %b     %h    %h   | %b    %h         %h     | %b ||    00000000", operandA,operandB, M, MxorB,carryoutin, overflow, carryout, andResult);
    operandA='hffffffff;operandB='hf00f001;M=1; #1000
    $display(" %b   %b     %h    %h   | %b    %h         %h     | %b ||    00000000", operandA,operandB, M, MxorB,carryoutin, overflow, carryout, andResult);
    operandA='hffffffff;operandB='hcccccccc;M=1; #1000
    $display(" %b   %b     %h    %h   | %b    %h         %h     | %b ||    00000000", operandA,operandB, M, MxorB,carryoutin, overflow, carryout, andResult);
    end
endmodule*/

/*module testsubtract();
    reg[31:0] a, b;
    wire[31:0] result;


    subtract32 myALU (result, a, b);

    initial begin
    //dump to vcd file so we can look at waveform
    $dumpfile("sub.vcd");
    $dumpvars(0, testsubtract);



    $display("Subtract Test:");
    $display("     a          b     |   result   ||   Exp result");

    a='h111;b='h101; #1000
    $display(" %h    %h |  %h  ", a, b, result);


    end
endmodule*/

/*module testsubtract();
    reg[31:0] a, b;
    wire[31:0] result;


    subtract32 myALU (result, a, b);

    initial begin
    //dump to vcd file so we can look at waveform
    $dumpfile("sub.vcd");
    $dumpvars(0, testsubtract);



    $display("Subtract Test:");
    $display("     a          b     |   result   ||   Exp result");

    a='h111;b='h101; #1000
    $display(" %h    %h |  %h  ", a, b, result);


    end
endmodule*/

/*module testxor();
    reg[31:0] a, b;
    wire[31:0] result;


    xor32 myALU (result, a, b);

    initial begin
    //dump to vcd file so we can look at waveform
    $dumpfile("xor.vcd");
    $dumpvars(0, testxor);



    $display("Subtract Test:");
    $display("     a          b     |   result   ||   Exp result");

    a='h111;b='h101; #1000
    $display(" %h    %h |  %h  ", a, b, result);


    end
endmodule*/

/*module testFullAdder() ;
    reg a, b, carryin, M;
    wire sum, carryout;

    structuralFullAdder adder (sum, carryout, a, b, carryin);


    initial begin
    $dumpfile("adder.vcd");
    $dumpvars(0, testFullAdder);

    $display("A B     M   | Sum Carryout | Expected Output");
    a=1;b=0;carryin=0;M=1; #1000
    $display("%b %b    %b    |    %b     %b   | 1  0", a, b, M, sum, carryout);
    a=1;b=1;carryin=0;M=1; #1000
    $display("%b %b    %b    |    %b     %b   | 0  0", a, b, M, sum, carryout);
    a=0;b=1;carryin=0; #1000
    $display("%b %b    %b    |    %b     %b   | 1  0", a, b, carryin, sum, carryout);
    a=0;b=1;carryin=1; #1000
    $display("%b %b    %b    |    %b     %b   | 0  1", a, b, carryin, sum, carryout);
    a=1;b=0;carryin=0; #1000
    $display("%b %b    %b    |    %b     %b   | 1  0", a, b, carryin, sum, carryout);
    a=1;b=0;carryin=1; #1000
    $display("%b %b    %b    |    %b     %b   | 0  1", a, b, carryin, sum, carryout);
    a=1;b=1;carryin=0; #1000
    $display("%b %b    %b    |    %b     %b   | 0  1", a, b, carryin, sum, carryout);
    a=1;b=1;carryin=1; #1000
    $display("%b %b    %b    |    %b     %b   | 1  1", a, b, carryin, sum, carryout);
    end
endmodule*/

alu.vcd
$date
	Mon Oct  3 22:37:48 2016
$end
$version
	Icarus Verilog
$end
$timescale
	1ps
$end
$scope module testor $end
$var wire 32 ! andResult [31:0] $end
$var wire 1 " carryout $end
$var wire 1 # overflow $end
$var reg 1 $ M $end
$var reg 32 % operandA [31:0] $end
$var reg 32 & operandB [31:0] $end
$scope module myALU $end
$var wire 1 ' M $end
$var wire 32 ( andResult [31:0] $end
$var wire 32 ) midResult [31:0] $end
$var wire 32 * operandA [31:0] $end
$var wire 32 + operandB [31:0] $end
$var reg 1 , carryout $end
$var reg 1 - overflow $end
$scope begin gen1[0] $end
$upscope $end
$scope begin gen1[1] $end
$upscope $end
$scope begin gen1[2] $end
$upscope $end
$scope begin gen1[3] $end
$upscope $end
$scope begin gen1[4] $end
$upscope $end
$scope begin gen1[5] $end
$upscope $end
$scope begin gen1[6] $end
$upscope $end
$scope begin gen1[7] $end
$upscope $end
$scope begin gen1[8] $end
$upscope $end
$scope begin gen1[9] $end
$upscope $end
$scope begin gen1[10] $end
$upscope $end
$scope begin gen1[11] $end
$upscope $end
$scope begin gen1[12] $end
$upscope $end
$scope begin gen1[13] $end
$upscope $end
$scope begin gen1[14] $end
$upscope $end
$scope begin gen1[15] $end
$upscope $end
$scope begin gen1[16] $end
$upscope $end
$scope begin gen1[17] $end
$upscope $end
$scope begin gen1[18] $end
$upscope $end
$scope begin gen1[19] $end
$upscope $end
$scope begin gen1[20] $end
$upscope $end
$scope begin gen1[21] $end
$upscope $end
$scope begin gen1[22] $end
$upscope $end
$scope begin gen1[23] $end
$upscope $end
$scope begin gen1[24] $end
$upscope $end
$scope begin gen1[25] $end
$upscope $end
$scope begin gen1[26] $end
$upscope $end
$scope begin gen1[27] $end
$upscope $end
$scope begin gen1[28] $end
$upscope $end
$scope begin gen1[29] $end
$upscope $end
$scope begin gen1[30] $end
$upscope $end
$scope begin gen1[31] $end
$upscope $end
$upscope $end
$upscope $end
$enddefinitions $end
#0
$dumpvars
0-
0,
b0 +
b0 *
bz )
bx (
1'
b0 &
b0 %
1$
0#
0"
bx !
$end
#30000
b0 )
#90000
b11111111111111111111111111111111 !
b11111111111111111111111111111111 (
#1000000
b1001100011 &
b1001100011 +
b110000001 %
b110000001 *
#1030000
b1111100011 )
#1090000
b11111111111111111111110000011100 !
b11111111111111111111110000011100 (
#2000000
b101100001 &
b101100001 +
b101100001 %
b101100001 *
#2030000
b101100001 )
#2090000
b11111111111111111111111010011110 !
b11111111111111111111111010011110 (
#3000000
b1111000000001111000000000001 &
b1111000000001111000000000001 +
b11111111111111111111111111111111 %
b11111111111111111111111111111111 *
#3030000
b11111111111111111111111111111111 )
#3090000
b0 !
b0 (
#4000000
b11001100110011001100110011001100 &
b11001100110011001100110011001100 +
